persian/__init__.py
persian/_version.py
persian/constants.py
persian/core.py
persian/deprecation.py
persian/persian.py
persian/py.typed
persian-1.1.0.dist-info/licenses/LICENSE
persian-1.1.0.dist-info/METADATA
persian-1.1.0.dist-info/WHEEL
persian-1.1.0.dist-info/top_level.txt
persian-1.1.0.dist-info/RECORD
