Metadata-Version: 2.4
Name: persian
Version: 1.1.0
Summary: Fast, typed Python library for Persian language localization
Author-email: Reza Kamali <hi@rez.nu>
Maintainer-email: Reza Kamali <hi@rez.nu>
License: MIT
Project-URL: Homepage, https://github.com/rezkam/persian
Project-URL: Documentation, https://persian.readthedocs.io
Project-URL: Repository, https://github.com/rezkam/persian
Project-URL: Issues, https://github.com/rezkam/persian/issues
Project-URL: Changelog, https://github.com/rezkam/persian/releases
Keywords: persian,farsi,localization,i18n,internationalization,arabic,numbers,characters,text-processing
Classifier: Development Status :: 5 - Production/Stable
Classifier: Intended Audience :: Developers
Classifier: License :: OSI Approved :: MIT License
Classifier: Operating System :: OS Independent
Classifier: Programming Language :: Python :: 3
Classifier: Programming Language :: Python :: 3 :: Only
Classifier: Programming Language :: Python :: 3.11
Classifier: Programming Language :: Python :: 3.12
Classifier: Programming Language :: Python :: 3.13
Classifier: Programming Language :: Python :: 3.14
Classifier: Programming Language :: Python :: 3.15
Classifier: Programming Language :: Python :: Implementation :: CPython
Classifier: Topic :: Software Development :: Libraries :: Python Modules
Classifier: Topic :: Software Development :: Localization
Classifier: Topic :: Software Development :: Internationalization
Classifier: Topic :: Text Processing :: Linguistic
Classifier: Topic :: Utilities
Classifier: Typing :: Typed
Requires-Python: >=3.11
License-File: LICENSE
Provides-Extra: dev
Requires-Dist: pytest>=9.0.2; extra == "dev"
Requires-Dist: pytest-cov>=7.0.0; extra == "dev"
Requires-Dist: pytest-benchmark>=5.2.3; extra == "dev"
Requires-Dist: ty>=0.0.11; extra == "dev"
Requires-Dist: ruff>=0.14.9; extra == "dev"
Requires-Dist: build>=1.3.0; extra == "dev"
Requires-Dist: setuptools-scm>=9.2.2; extra == "dev"
Provides-Extra: docs
Requires-Dist: sphinx>=9.0.4; extra == "docs"
Requires-Dist: sphinx-autodoc-typehints>=3.6.0; extra == "docs"
Requires-Dist: pydata-sphinx-theme>=0.16.1; extra == "docs"
Dynamic: license-file
